Metadata-Version: 1.0
Name: thjo-distributions
Version: 1.2
Summary: Gaussian and Binomial distributions
Home-page: UNKNOWN
Author: Jonas Theiler
Author-email: someemail@something.com
License: UNKNOWN
Platform: UNKNOWN
